helloworld_lib/__init__.py
helloworld_lib/hello.py
helloworld_lib_sankar-0.1.0.dist-info/licenses/LICENSE
helloworld_lib_sankar-0.1.0.dist-info/METADATA
helloworld_lib_sankar-0.1.0.dist-info/WHEEL
helloworld_lib_sankar-0.1.0.dist-info/top_level.txt
helloworld_lib_sankar-0.1.0.dist-info/RECORD
